autoplotter/__init__.py
autoplotter/app.py
autoplotter/data_exploration.py
autoplotter/homepage.py
autoplotter/navbar.py
autoplotter/plots.py
autoplotter-0.0.2.dist-info/LICENSE
autoplotter-0.0.2.dist-info/METADATA
autoplotter-0.0.2.dist-info/WHEEL
autoplotter-0.0.2.dist-info/top_level.txt
autoplotter-0.0.2.dist-info/RECORD
