Metadata-Version: 2.1
Name: autoplotter
Version: 0.0.2
Summary: Useful tool for GUI Based EDA
Home-page: https://github.com/ersaurabhverma/autoplotter
Author: Saurabh Verma
Author-email: verma.saurabh8010@gmail.com
License: MIT
Download-URL: https://pypi.org/project/autoplotter/
Keywords: EDA,Python,Plotly,Gui EDA
Platform: UNKNOWN
Requires-Dist: dash
Requires-Dist: plotly
Requires-Dist: jupyter-dash
Requires-Dist: dash-bootstrap-components
Requires-Dist: pandas
Requires-Dist: dash-table
Requires-Dist: dash-core-components
Requires-Dist: dash-html-components
Requires-Dist: ppscore
Requires-Dist: numpy
